{
    "Ar36": {
        "error": 0.0005442677488476393,
        "error_type": "SEM",
        "filter_outliers_dict": {
            "filter_outliers": true,
            "iterations": 1,
            "std_devs": 2,
            "use_standard_deviation_filtering": false
        },
        "fit": "parabolic",
        "value": 0.010097408131711111
    },
    "Ar37": {
        "error": 0.02111442812652165,
        "error_type": "SEM",
        "filter_outliers_dict": {
            "filter_outliers": true,
            "iterations": 1,
            "std_devs": 2,
            "use_standard_deviation_filtering": false
        },
        "fit": "linear",
        "value": 0.05510100850979013
    },
    "Ar38": {
        "error": 0.022945251756795647,
        "error_type": "SEM",
        "filter_outliers_dict": {
            "filter_outliers": true,
            "iterations": 1,
            "std_devs": 2,
            "use_standard_deviation_filtering": false
        },
        "fit": "linear",
        "value": 1.160321887639546
    },
    "Ar39": {
        "error": 0.07240730733976414,
        "error_type": "SEM",
        "filter_outliers_dict": {
            "filter_outliers": true,
            "iterations": 1,
            "std_devs": 2,
            "use_standard_deviation_filtering": false
        },
        "fit": "parabolic",
        "value": 99.42523162357513
    },
    "Ar40": {
        "error": 0.24242910499639414,
        "error_type": "SEM",
        "filter_outliers_dict": {
            "filter_outliers": true,
            "iterations": 1,
            "std_devs": 2,
            "use_standard_deviation_filtering": false
        },
        "fit": "parabolic",
        "value": 3242.3428099820067
    },
    "Ar41": {
        "error": 0.010062155578615171,
        "error_type": "SEM",
        "filter_outliers_dict": {
            "filter_outliers": true,
            "iterations": 1,
            "std_devs": 2,
            "use_standard_deviation_filtering": false
        },
        "fit": "average",
        "value": 0.01773716170195409
    }
}