{
    "AX": {
        "error": 0.011657969495766954,
        "error_type": "SEM",
        "filter_outliers_dict": {
            "filter_outliers": true,
            "iterations": 1,
            "std_devs": 2,
            "use_standard_deviation_filtering": false
        },
        "fit": "average",
        "value": -0.024456466930463317
    },
    "CDD": {
        "error": 1.5695904698994682e-05,
        "error_type": "SEM",
        "filter_outliers_dict": {
            "filter_outliers": true,
            "iterations": 1,
            "std_devs": 2,
            "use_standard_deviation_filtering": false
        },
        "fit": "average",
        "value": 0.00016370942051123296
    },
    "H1": {
        "error": 0.011706779237622835,
        "error_type": "SEM",
        "filter_outliers_dict": {
            "filter_outliers": true,
            "iterations": 1,
            "std_devs": 2,
            "use_standard_deviation_filtering": false
        },
        "fit": "average",
        "value": 0.10749316313440967
    },
    "H2": {
        "error": 0.012202284869099909,
        "error_type": "SEM",
        "filter_outliers_dict": {
            "filter_outliers": true,
            "iterations": 1,
            "std_devs": 2,
            "use_standard_deviation_filtering": false
        },
        "fit": "average",
        "value": -0.06969879513831231
    },
    "L1": {
        "error": 0.011855966206711557,
        "error_type": "SEM",
        "filter_outliers_dict": {
            "filter_outliers": true,
            "iterations": 1,
            "std_devs": 2,
            "use_standard_deviation_filtering": false
        },
        "fit": "average",
        "value": -0.1307196541064596
    },
    "L2": {
        "error": 0.009926477436231396,
        "error_type": "SEM",
        "filter_outliers_dict": {
            "filter_outliers": true,
            "iterations": 1,
            "std_devs": 2,
            "use_standard_deviation_filtering": false
        },
        "fit": "average",
        "value": 0.01376413307229728
    }
}